{"results":{"DumbPlayer":{"result":"Loss","score":"0"},"SmartPlayer":{"result":"Win","score":"1"}},"moves":[{"description":"DumbPlayer moves F6:E7","data":"['DumbPlayer', 'F6:E7']"},{"description":"SmartPlayer moves C1:D0","data":"['SmartPlayer', 'C1:D0']"},{"description":"DumbPlayer moves F4:E5","data":"['DumbPlayer', 'F4:E5']"},{"description":"SmartPlayer moves C5:D6","data":"['SmartPlayer', 'C5:D6']"},{"description":"DumbPlayer moves E7:C5","data":"['DumbPlayer', 'E7:C5']"},{"description":"SmartPlayer moves B4:D6:F4","data":"['SmartPlayer', 'B4:D6:F4']"},{"description":"DumbPlayer moves G3:E5","data":"['DumbPlayer', 'G3:E5']"},{"description":"SmartPlayer moves B0:C1","data":"['SmartPlayer', 'B0:C1']"},{"description":"DumbPlayer moves G7:F6","data":"['DumbPlayer', 'G7:F6']"},{"description":"SmartPlayer moves A1:B0","data":"['SmartPlayer', 'A1:B0']","gamestate":"[[0, 0, 0, 1, 0, 1, 0, 1], [1, 0, 1, 0, 0, 0, 1, 0], [0, 1, 0, 1, 0, 0, 0, 1], [1, 0, 0, 0, 0, 0, 0, 0], [0, 0, 0, 0, 0, 3, 0, 0], [3, 0, 3, 0, 0, 0, 3, 0], [0, 3, 0, 0, 0, 3, 0, 0], [3, 0, 3, 0, 3, 0, 3, 0]]"},{"description":"DumbPlayer moves F6:E7","data":"['DumbPlayer', 'F6:E7']"},{"description":"SmartPlayer moves B6:C5","data":"['SmartPlayer', 'B6:C5']"},{"description":"DumbPlayer moves H6:G7","data":"['DumbPlayer', 'H6:G7']"},{"description":"SmartPlayer moves C5:D4","data":"['SmartPlayer', 'C5:D4']"},{"description":"DumbPlayer moves G7:F6","data":"['DumbPlayer', 'G7:F6']"},{"description":"SmartPlayer moves A3:B4","data":"['SmartPlayer', 'A3:B4']"},{"description":"DumbPlayer moves F0:E1","data":"['DumbPlayer', 'F0:E1']"},{"description":"SmartPlayer moves C1:D2","data":"['SmartPlayer', 'C1:D2']"},{"description":"DumbPlayer moves G1:F0","data":"['DumbPlayer', 'G1:F0']"},{"description":"SmartPlayer moves D2:E3","data":"['SmartPlayer', 'D2:E3']","gamestate":"[[0, 0, 0, 0, 0, 1, 0, 1], [1, 0, 1, 0, 1, 0, 0, 0], [0, 0, 0, 1, 0, 0, 0, 1], [1, 0, 0, 0, 1, 0, 0, 0], [0, 3, 0, 1, 0, 3, 0, 3], [3, 0, 3, 0, 0, 0, 3, 0], [0, 0, 0, 0, 0, 3, 0, 0], [3, 0, 3, 0, 3, 0, 0, 0]]"},{"description":"DumbPlayer moves H0:G1","data":"['DumbPlayer', 'H0:G1']"},{"description":"SmartPlayer moves A5:B6","data":"['SmartPlayer', 'A5:B6']"},{"description":"DumbPlayer moves E7:D6","data":"['DumbPlayer', 'E7:D6']"},{"description":"SmartPlayer moves B6:C5","data":"['SmartPlayer', 'B6:C5']"},{"description":"DumbPlayer moves F6:E7","data":"['DumbPlayer', 'F6:E7']"},{"description":"SmartPlayer moves D4:F6","data":"['SmartPlayer', 'D4:F6']"},{"description":"DumbPlayer moves F2:D4:B6","data":"['DumbPlayer', 'F2:D4:B6']"},{"description":"SmartPlayer moves D0:F2:H0","data":"['SmartPlayer', 'D0:F2:H0']"},{"description":"DumbPlayer moves D6:C5","data":"['DumbPlayer', 'D6:C5']"},{"description":"SmartPlayer moves B4:D6","data":"['SmartPlayer', 'B4:D6']","gamestate":"[[0, 0, 0, 0, 0, 0, 0, 1], [1, 0, 1, 0, 0, 0, 3, 0], [0, 0, 0, 1, 0, 0, 0, 1], [0, 0, 0, 0, 0, 0, 1, 0], [0, 0, 0, 0, 0, 0, 0, 3], [3, 0, 0, 0, 0, 0, 1, 0], [0, 0, 0, 0, 0, 3, 0, 0], [2, 0, 3, 0, 3, 0, 0, 0]]"},{"description":"DumbPlayer moves E7:C5","data":"['DumbPlayer', 'E7:C5']"},{"description":"SmartPlayer moves F6:G7","data":"['SmartPlayer', 'F6:G7']"},{"description":"DumbPlayer moves B6:A5","data":"['DumbPlayer', 'B6:A5']"},{"description":"SmartPlayer moves G7:H6","data":"['SmartPlayer', 'G7:H6']"},{"description":"DumbPlayer moves G5:F4","data":"['DumbPlayer', 'G5:F4']"},{"description":"SmartPlayer moves C3:D4","data":"['SmartPlayer', 'C3:D4']"},{"description":"DumbPlayer moves H2:G3","data":"['DumbPlayer', 'H2:G3']"},{"description":"SmartPlayer moves D4:E5","data":"['SmartPlayer', 'D4:E5']"},{"description":"DumbPlayer moves F4:D6","data":"['DumbPlayer', 'F4:D6']"},{"description":"SmartPlayer moves C7:E5","data":"['SmartPlayer', 'C7:E5']","gamestate":"[[0, 0, 0, 0, 0, 4, 0, 1], [1, 0, 1, 0, 0, 0, 0, 0], [0, 0, 0, 0, 0, 3, 0, 0], [0, 0, 0, 0, 0, 0, 0, 0], [0, 0, 0, 0, 0, 1, 0, 0], [3, 0, 0, 0, 0, 0, 0, 0], [0, 0, 0, 3, 0, 0, 0, 0], [2, 0, 0, 0, 3, 0, 2, 0]]"},{"description":"DumbPlayer moves F0:E1","data":"['DumbPlayer', 'F0:E1']"},{"description":"SmartPlayer moves B2:C1","data":"['SmartPlayer', 'B2:C1']"},{"description":"DumbPlayer moves E1:D0","data":"['DumbPlayer', 'E1:D0']"},{"description":"SmartPlayer moves C1:D2","data":"['SmartPlayer', 'C1:D2']"},{"description":"DumbPlayer moves D0:C1","data":"['DumbPlayer', 'D0:C1']"},{"description":"SmartPlayer moves D2:E3","data":"['SmartPlayer', 'D2:E3']"},{"description":"DumbPlayer moves C1:B2","data":"['DumbPlayer', 'C1:B2']"},{"description":"SmartPlayer moves E3:F4","data":"['SmartPlayer', 'E3:F4']"},{"description":"DumbPlayer moves B2:A1","data":"['DumbPlayer', 'B2:A1']"},{"description":"SmartPlayer moves F4:H2","data":"['SmartPlayer', 'F4:H2']","gamestate":"[[0, 4, 0, 0, 0, 4, 0, 1], [1, 0, 0, 0, 0, 0, 0, 0], [0, 0, 0, 0, 0, 3, 0, 0], [0, 0, 0, 0, 0, 0, 0, 0], [0, 0, 0, 0, 0, 1, 0, 0], [0, 0, 0, 0, 0, 0, 0, 0], [0, 0, 0, 0, 0, 0, 0, 0], [2, 0, 2, 0, 3, 0, 2, 0]]"},{"description":"DumbPlayer moves A5:B4","data":"['DumbPlayer', 'A5:B4']"},{"description":"SmartPlayer moves H6:G7","data":"['SmartPlayer', 'H6:G7']"},{"description":"DumbPlayer moves B4:C3","data":"['DumbPlayer', 'B4:C3']"},{"description":"SmartPlayer moves B0:C1","data":"['SmartPlayer', 'B0:C1']"},{"description":"DumbPlayer moves A1:B0","data":"['DumbPlayer', 'A1:B0']"},{"description":"SmartPlayer moves C1:D0","data":"['SmartPlayer', 'C1:D0']"},{"description":"DumbPlayer moves C3:B4","data":"['DumbPlayer', 'C3:B4']"},{"description":"SmartPlayer moves H2:G1","data":"['SmartPlayer', 'H2:G1']"},{"description":"DumbPlayer moves B0:C1","data":"['DumbPlayer', 'B0:C1']"},{"description":"SmartPlayer moves G1:F0","data":"['SmartPlayer', 'G1:F0']","gamestate":"[[0, 0, 0, 0, 0, 0, 0, 1], [0, 0, 0, 0, 4, 0, 0, 0], [0, 4, 0, 0, 0, 3, 0, 0], [1, 0, 0, 0, 0, 0, 0, 0], [0, 0, 0, 0, 0, 1, 0, 0], [2, 0, 0, 0, 0, 0, 0, 0], [0, 0, 0, 0, 0, 0, 0, 2], [2, 0, 0, 0, 3, 0, 0, 0]]"},{"description":"DumbPlayer moves C1:B0","data":"['DumbPlayer', 'C1:B0']"},{"description":"SmartPlayer moves D0:E1","data":"['SmartPlayer', 'D0:E1']"},{"description":"DumbPlayer moves B0:A1","data":"['DumbPlayer', 'B0:A1']"},{"description":"SmartPlayer moves H0:G1","data":"['SmartPlayer', 'H0:G1']"},{"description":"DumbPlayer moves A1:B0","data":"['DumbPlayer', 'A1:B0']"},{"description":"SmartPlayer moves G1:F2","data":"['SmartPlayer', 'G1:F2']"},{"description":"DumbPlayer moves B0:A1","data":"['DumbPlayer', 'B0:A1']"},{"description":"SmartPlayer moves E5:F4","data":"['SmartPlayer', 'E5:F4']"},{"description":"DumbPlayer moves A1:B0","data":"['DumbPlayer', 'A1:B0']"},{"description":"SmartPlayer moves F4:G5","data":"['SmartPlayer', 'F4:G5']","gamestate":"[[0, 0, 0, 0, 0, 0, 0, 1], [4, 0, 0, 0, 4, 0, 0, 0], [0, 0, 0, 0, 0, 3, 0, 0], [0, 0, 0, 0, 0, 0, 0, 0], [0, 1, 0, 0, 0, 0, 0, 0], [2, 0, 2, 0, 0, 0, 0, 0], [0, 0, 0, 0, 0, 1, 0, 2], [0, 0, 0, 0, 3, 0, 0, 0]]"},{"description":"DumbPlayer moves H4:F6","data":"['DumbPlayer', 'H4:F6']"},{"description":"SmartPlayer moves G7:E5","data":"['SmartPlayer', 'G7:E5']"},{"description":"DumbPlayer moves B4:A3","data":"['DumbPlayer', 'B4:A3']"},{"description":"SmartPlayer moves E5:D4","data":"['SmartPlayer', 'E5:D4']"},{"description":"DumbPlayer moves C5:B6","data":"['DumbPlayer', 'C5:B6']"},{"description":"SmartPlayer moves A7:C5","data":"['SmartPlayer', 'A7:C5']"},{"description":"DumbPlayer moves A3:B4","data":"['DumbPlayer', 'A3:B4']"},{"description":"SmartPlayer moves C5:D6","data":"['SmartPlayer', 'C5:D6']"},{"description":"DumbPlayer moves B0:C1","data":"['DumbPlayer', 'B0:C1']"},{"description":"SmartPlayer moves D4:C5","data":"['SmartPlayer', 'D4:C5']","gamestate":"[[0, 0, 0, 0, 0, 0, 0, 0], [0, 0, 0, 0, 4, 0, 0, 0], [0, 4, 0, 0, 0, 2, 0, 0], [0, 0, 0, 0, 0, 0, 1, 0], [0, 1, 0, 0, 0, 0, 0, 0], [2, 0, 2, 0, 0, 0, 0, 0], [0, 0, 0, 0, 0, 0, 0, 0], [0, 0, 0, 0, 0, 0, 0, 0]]"},{"description":"DumbPlayer moves B4:A3","data":"['DumbPlayer', 'B4:A3']"},{"description":"SmartPlayer moves D6:E7","data":"['SmartPlayer', 'D6:E7']"},{"description":"DumbPlayer moves C1:B0","data":"['DumbPlayer', 'C1:B0']"},{"description":"SmartPlayer moves F2:E3","data":"['SmartPlayer', 'F2:E3']"},{"description":"DumbPlayer moves B0:A1","data":"['DumbPlayer', 'B0:A1']"},{"description":"SmartPlayer moves E1:F2","data":"['SmartPlayer', 'E1:F2']"},{"description":"DumbPlayer moves A1:B0","data":"['DumbPlayer', 'A1:B0']"},{"description":"SmartPlayer moves F2:G1","data":"['SmartPlayer', 'F2:G1']"},{"description":"DumbPlayer moves B0:C1","data":"['DumbPlayer', 'B0:C1']"},{"description":"SmartPlayer moves G1:H2","data":"['SmartPlayer', 'G1:H2']","gamestate":"[[0, 0, 0, 4, 0, 0, 0, 0], [0, 0, 0, 0, 0, 0, 0, 0], [0, 4, 0, 0, 0, 2, 0, 0], [0, 0, 0, 0, 0, 0, 0, 0], [0, 0, 0, 2, 0, 0, 0, 1], [2, 0, 0, 0, 0, 0, 0, 0], [0, 0, 0, 0, 0, 0, 0, 0], [0, 0, 2, 0, 0, 0, 0, 0]]"},{"description":"DumbPlayer moves C1:B0","data":"['DumbPlayer', 'C1:B0']"},{"description":"SmartPlayer moves H2:G3","data":"['SmartPlayer', 'H2:G3']"},{"description":"DumbPlayer moves B0:A1","data":"['DumbPlayer', 'B0:A1']"},{"description":"SmartPlayer moves C5:B6","data":"['SmartPlayer', 'C5:B6']"},{"description":"DumbPlayer moves A1:B0","data":"['DumbPlayer', 'A1:B0']"},{"description":"SmartPlayer moves G3:F2","data":"['SmartPlayer', 'G3:F2']"},{"description":"DumbPlayer moves A3:B4","data":"['DumbPlayer', 'A3:B4']"},{"description":"SmartPlayer moves B6:A5","data":"['SmartPlayer', 'B6:A5']"},{"description":"DumbPlayer moves B4:C3","data":"['DumbPlayer', 'B4:C3']"},{"description":"SmartPlayer moves F0:E1","data":"['SmartPlayer', 'F0:E1']","gamestate":"[[0, 0, 0, 0, 0, 2, 0, 0], [4, 0, 0, 0, 0, 0, 0, 0], [0, 0, 0, 4, 0, 0, 0, 0], [0, 0, 0, 0, 0, 0, 0, 0], [0, 2, 0, 2, 0, 0, 0, 1], [0, 0, 2, 0, 0, 0, 0, 0], [0, 0, 0, 0, 0, 0, 0, 0], [0, 0, 0, 0, 0, 0, 0, 0]]"},{"description":"DumbPlayer moves C3:B2","data":"['DumbPlayer', 'C3:B2']"},{"description":"SmartPlayer moves A5:B4","data":"['SmartPlayer', 'A5:B4']"},{"description":"DumbPlayer moves B2:A3","data":"['DumbPlayer', 'B2:A3']"},{"description":"SmartPlayer moves B4:A5","data":"['SmartPlayer', 'B4:A5']"},{"description":"DumbPlayer moves B0:A1","data":"['DumbPlayer', 'B0:A1']"},{"description":"SmartPlayer moves E1:D0","data":"['SmartPlayer', 'E1:D0']"},{"description":"DumbPlayer moves A1:B0","data":"['DumbPlayer', 'A1:B0']"},{"description":"SmartPlayer moves E3:D4","data":"['SmartPlayer', 'E3:D4']"},{"description":"DumbPlayer moves A3:B2","data":"['DumbPlayer', 'A3:B2']"},{"description":"SmartPlayer moves A5:B4","data":"['SmartPlayer', 'A5:B4']","gamestate":"[[0, 0, 0, 0, 0, 0, 0, 0], [4, 0, 4, 0, 2, 0, 0, 0], [0, 0, 0, 0, 0, 0, 0, 0], [2, 0, 0, 0, 2, 0, 0, 0], [0, 0, 0, 0, 0, 0, 0, 1], [0, 0, 2, 0, 0, 0, 0, 0], [0, 0, 0, 0, 0, 0, 0, 0], [0, 0, 0, 0, 0, 0, 0, 0]]"},{"description":"DumbPlayer moves B2:A3","data":"['DumbPlayer', 'B2:A3']"},{"description":"SmartPlayer moves F2:E3","data":"['SmartPlayer', 'F2:E3']"},{"description":"DumbPlayer moves A3:C5","data":"['DumbPlayer', 'A3:C5']"},{"description":"SmartPlayer moves D4:B6","data":"['SmartPlayer', 'D4:B6']"},{"description":"DumbPlayer moves B0:A1","data":"['DumbPlayer', 'B0:A1']"},{"description":"SmartPlayer moves D0:C1","data":"['SmartPlayer', 'D0:C1']"},{"description":"DumbPlayer moves A1:B0","data":"['DumbPlayer', 'A1:B0']"},{"description":"SmartPlayer moves C1:B2","data":"['SmartPlayer', 'C1:B2']"},{"description":"DumbPlayer moves B0:A1","data":"['DumbPlayer', 'B0:A1']"},{"description":"SmartPlayer moves B2:A3","data":"['SmartPlayer', 'B2:A3']","gamestate":"[[0, 4, 0, 2, 0, 0, 0, 0], [0, 0, 0, 0, 0, 0, 2, 0], [0, 0, 0, 0, 0, 0, 0, 0], [0, 0, 0, 0, 0, 0, 0, 0], [0, 0, 0, 2, 0, 0, 0, 1], [0, 0, 0, 0, 0, 0, 0, 0], [0, 0, 0, 0, 0, 0, 0, 0], [0, 0, 0, 0, 0, 0, 0, 0]]"},{"description":"DumbPlayer moves A1:B0","data":"['DumbPlayer', 'A1:B0']"},{"description":"SmartPlayer moves A3:B2","data":"['SmartPlayer', 'A3:B2']"},{"description":"DumbPlayer moves B0:A1","data":"['DumbPlayer', 'B0:A1']"},{"description":"SmartPlayer moves B2:C3","data":"['SmartPlayer', 'B2:C3']"},{"description":"DumbPlayer moves A1:B0","data":"['DumbPlayer', 'A1:B0']"},{"description":"SmartPlayer moves E3:D4","data":"['SmartPlayer', 'E3:D4']"},{"description":"DumbPlayer moves B0:A1","data":"['DumbPlayer', 'B0:A1']"},{"description":"SmartPlayer moves C3:B4","data":"['SmartPlayer', 'C3:B4']"},{"description":"DumbPlayer moves A1:B0","data":"['DumbPlayer', 'A1:B0']"},{"description":"SmartPlayer moves B4:A3","data":"['SmartPlayer', 'B4:A3']","gamestate":"[[0, 0, 0, 2, 0, 0, 0, 0], [4, 0, 0, 0, 0, 0, 2, 0], [0, 0, 0, 0, 0, 0, 0, 0], [0, 0, 0, 0, 2, 0, 0, 0], [0, 0, 0, 0, 0, 0, 0, 1], [0, 0, 0, 0, 0, 0, 0, 0], [0, 0, 0, 0, 0, 0, 0, 0], [0, 0, 0, 0, 0, 0, 0, 0]]"},{"description":"DumbPlayer moves B0:A1","data":"['DumbPlayer', 'B0:A1']"},{"description":"SmartPlayer moves A3:B4","data":"['SmartPlayer', 'A3:B4']"},{"description":"DumbPlayer moves A1:B0","data":"['DumbPlayer', 'A1:B0']"},{"description":"SmartPlayer moves B4:C5","data":"['SmartPlayer', 'B4:C5']"},{"description":"DumbPlayer moves B0:A1","data":"['DumbPlayer', 'B0:A1']"},{"description":"SmartPlayer moves B6:A7","data":"['SmartPlayer', 'B6:A7']"},{"description":"DumbPlayer moves A1:B0","data":"['DumbPlayer', 'A1:B0']"},{"description":"SmartPlayer moves D4:C3","data":"['SmartPlayer', 'D4:C3']"},{"description":"DumbPlayer moves B0:C1","data":"['DumbPlayer', 'B0:C1']"},{"description":"SmartPlayer moves C5:D4","data":"['SmartPlayer', 'C5:D4']","gamestate":"[[0, 0, 0, 0, 0, 0, 0, 2], [0, 0, 0, 0, 0, 0, 0, 0], [0, 4, 0, 2, 0, 0, 0, 0], [0, 0, 0, 0, 2, 0, 0, 0], [0, 0, 0, 0, 0, 0, 0, 1], [0, 0, 0, 0, 0, 0, 0, 0], [0, 0, 0, 0, 0, 0, 0, 0], [0, 0, 0, 0, 0, 0, 0, 0]]"},{"description":"DumbPlayer moves C1:B0","data":"['DumbPlayer', 'C1:B0']"},{"description":"SmartPlayer moves E7:F6","data":"['SmartPlayer', 'E7:F6']"},{"description":"DumbPlayer moves B0:C1","data":"['DumbPlayer', 'B0:C1']"},{"description":"SmartPlayer moves F6:G7","data":"['SmartPlayer', 'F6:G7']"},{"description":"DumbPlayer moves C1:B0","data":"['DumbPlayer', 'C1:B0']"},{"description":"SmartPlayer moves G7:H6","data":"['SmartPlayer', 'G7:H6']"},{"description":"DumbPlayer moves B0:C1","data":"['DumbPlayer', 'B0:C1']"},{"description":"SmartPlayer moves H6:G5","data":"['SmartPlayer', 'H6:G5']"},{"description":"DumbPlayer moves C1:B0","data":"['DumbPlayer', 'C1:B0']"},{"description":"SmartPlayer moves D4:C5","data":"['SmartPlayer', 'D4:C5']","gamestate":"[[0, 0, 0, 0, 0, 0, 0, 2], [4, 0, 0, 0, 0, 0, 0, 0], [0, 0, 0, 2, 0, 2, 0, 0], [0, 0, 0, 0, 0, 0, 0, 0], [0, 0, 0, 0, 0, 0, 0, 0], [0, 0, 0, 0, 0, 0, 0, 0], [0, 0, 0, 0, 0, 2, 0, 0], [0, 0, 0, 0, 0, 0, 0, 0]]"},{"description":"DumbPlayer moves B0:A1","data":"['DumbPlayer', 'B0:A1']"},{"description":"SmartPlayer moves G5:F4","data":"['SmartPlayer', 'G5:F4']"},{"description":"DumbPlayer moves A1:B0","data":"['DumbPlayer', 'A1:B0']"},{"description":"SmartPlayer moves F4:E3","data":"['SmartPlayer', 'F4:E3']"},{"description":"DumbPlayer moves B0:A1","data":"['DumbPlayer', 'B0:A1']"},{"description":"SmartPlayer moves C5:B6","data":"['SmartPlayer', 'C5:B6']"},{"description":"DumbPlayer moves A1:B0","data":"['DumbPlayer', 'A1:B0']"},{"description":"SmartPlayer moves E3:D4","data":"['SmartPlayer', 'E3:D4']"},{"description":"DumbPlayer moves B0:C1","data":"['DumbPlayer', 'B0:C1']"},{"description":"SmartPlayer moves C3:B4","data":"['SmartPlayer', 'C3:B4']","gamestate":"[[0, 0, 0, 0, 0, 0, 0, 2], [0, 0, 0, 0, 2, 0, 2, 0], [0, 4, 0, 0, 0, 0, 0, 0], [0, 0, 0, 0, 2, 0, 0, 0], [0, 0, 0, 0, 0, 0, 0, 0], [0, 0, 0, 0, 0, 0, 0, 0], [0, 0, 0, 0, 0, 0, 0, 0], [0, 0, 0, 0, 0, 0, 0, 0]]"},{"description":"DumbPlayer moves C1:B0","data":"['DumbPlayer', 'C1:B0']"},{"description":"SmartPlayer moves B4:C3","data":"['SmartPlayer', 'B4:C3']"},{"description":"DumbPlayer moves B0:C1","data":"['DumbPlayer', 'B0:C1']"},{"description":"SmartPlayer moves C3:B4","data":"['SmartPlayer', 'C3:B4']"},{"description":"DumbPlayer moves C1:B0","data":"['DumbPlayer', 'C1:B0']"},{"description":"SmartPlayer moves B4:A5","data":"['SmartPlayer', 'B4:A5']"},{"description":"DumbPlayer moves B0:C1","data":"['DumbPlayer', 'B0:C1']"},{"description":"SmartPlayer moves B6:C7","data":"['SmartPlayer', 'B6:C7']"},{"description":"DumbPlayer moves C1:B0","data":"['DumbPlayer', 'C1:B0']"},{"description":"SmartPlayer moves D4:C5","data":"['SmartPlayer', 'D4:C5']","gamestate":"[[0, 0, 0, 0, 0, 2, 0, 2], [4, 0, 0, 0, 0, 0, 0, 0], [0, 0, 0, 0, 0, 2, 0, 2], [0, 0, 0, 0, 0, 0, 0, 0], [0, 0, 0, 0, 0, 0, 0, 0], [0, 0, 0, 0, 0, 0, 0, 0], [0, 0, 0, 0, 0, 0, 0, 0], [0, 0, 0, 0, 0, 0, 0, 0]]"},{"description":"DumbPlayer moves B0:C1","data":"['DumbPlayer', 'B0:C1']"},{"description":"SmartPlayer moves C7:B6","data":"['SmartPlayer', 'C7:B6']"},{"description":"DumbPlayer moves C1:B0","data":"['DumbPlayer', 'C1:B0']"},{"description":"SmartPlayer moves B6:C7","data":"['SmartPlayer', 'B6:C7']"},{"description":"DumbPlayer moves B0:C1","data":"['DumbPlayer', 'B0:C1']"},{"description":"SmartPlayer moves C7:B6","data":"['SmartPlayer', 'C7:B6']"},{"description":"DumbPlayer moves C1:B0","data":"['DumbPlayer', 'C1:B0']"},{"description":"SmartPlayer moves C5:B4","data":"['SmartPlayer', 'C5:B4']"},{"description":"DumbPlayer moves B0:A1","data":"['DumbPlayer', 'B0:A1']"},{"description":"SmartPlayer moves B4:A3","data":"['SmartPlayer', 'B4:A3']","gamestate":"[[0, 4, 0, 2, 0, 2, 0, 2], [0, 0, 0, 0, 0, 0, 2, 0], [0, 0, 0, 0, 0, 0, 0, 0], [0, 0, 0, 0, 0, 0, 0, 0], [0, 0, 0, 0, 0, 0, 0, 0], [0, 0, 0, 0, 0, 0, 0, 0], [0, 0, 0, 0, 0, 0, 0, 0], [0, 0, 0, 0, 0, 0, 0, 0]]"},{"description":"DumbPlayer moves A1:B0","data":"['DumbPlayer', 'A1:B0']"},{"description":"SmartPlayer moves B6:C7","data":"['SmartPlayer', 'B6:C7']"},{"description":"DumbPlayer moves B0:A1","data":"['DumbPlayer', 'B0:A1']"},{"description":"SmartPlayer moves A3:B4","data":"['SmartPlayer', 'A3:B4']"},{"description":"DumbPlayer moves A1:B0","data":"['DumbPlayer', 'A1:B0']"},{"description":"SmartPlayer moves C7:B6","data":"['SmartPlayer', 'C7:B6']"},{"description":"DumbPlayer moves B0:A1","data":"['DumbPlayer', 'B0:A1']"},{"description":"SmartPlayer moves B4:A3","data":"['SmartPlayer', 'B4:A3']"},{"description":"DumbPlayer moves A1:B0","data":"['DumbPlayer', 'A1:B0']"},{"description":"SmartPlayer moves A3:B2","data":"['SmartPlayer', 'A3:B2']","gamestate":"[[0, 0, 0, 0, 0, 2, 0, 2], [4, 0, 2, 0, 0, 0, 2, 0], [0, 0, 0, 0, 0, 0, 0, 0], [0, 0, 0, 0, 0, 0, 0, 0], [0, 0, 0, 0, 0, 0, 0, 0], [0, 0, 0, 0, 0, 0, 0, 0], [0, 0, 0, 0, 0, 0, 0, 0], [0, 0, 0, 0, 0, 0, 0, 0]]"},{"description":"DumbPlayer moves B0:A1","data":"['DumbPlayer', 'B0:A1']"},{"description":"SmartPlayer moves B2:A3","data":"['SmartPlayer', 'B2:A3']"},{"description":"DumbPlayer moves A1:B0","data":"['DumbPlayer', 'A1:B0']"},{"description":"SmartPlayer moves A3:B2","data":"['SmartPlayer', 'A3:B2']"},{"description":"DumbPlayer moves B0:A1","data":"['DumbPlayer', 'B0:A1']"},{"description":"SmartPlayer moves B2:A3","data":"['SmartPlayer', 'B2:A3']"},{"description":"DumbPlayer moves A1:B0","data":"['DumbPlayer', 'A1:B0']"},{"description":"SmartPlayer moves B6:C7","data":"['SmartPlayer', 'B6:C7']"},{"description":"DumbPlayer moves B0:A1","data":"['DumbPlayer', 'B0:A1']"},{"description":"SmartPlayer moves A5:B4","data":"['SmartPlayer', 'A5:B4']","gamestate":"[[0, 4, 0, 2, 0, 0, 0, 2], [0, 0, 0, 0, 2, 0, 0, 0], [0, 0, 0, 0, 0, 0, 0, 2], [0, 0, 0, 0, 0, 0, 0, 0], [0, 0, 0, 0, 0, 0, 0, 0], [0, 0, 0, 0, 0, 0, 0, 0], [0, 0, 0, 0, 0, 0, 0, 0], [0, 0, 0, 0, 0, 0, 0, 0]]"},{"description":"DumbPlayer moves A1:B0","data":"['DumbPlayer', 'A1:B0']"},{"description":"SmartPlayer moves B4:C5","data":"['SmartPlayer', 'B4:C5']"},{"description":"DumbPlayer moves B0:A1","data":"['DumbPlayer', 'B0:A1']"},{"description":"SmartPlayer moves C7:B6","data":"['SmartPlayer', 'C7:B6']"},{"description":"DumbPlayer moves A1:B0","data":"['DumbPlayer', 'A1:B0']"},{"description":"SmartPlayer moves C5:B4","data":"['SmartPlayer', 'C5:B4']"},{"description":"DumbPlayer moves B0:A1","data":"['DumbPlayer', 'B0:A1']"},{"description":"SmartPlayer moves B6:A5","data":"['SmartPlayer', 'B6:A5']"},{"description":"DumbPlayer moves A1:B0","data":"['DumbPlayer', 'A1:B0']"},{"description":"SmartPlayer moves B4:C5","data":"['SmartPlayer', 'B4:C5']","gamestate":"[[0, 0, 0, 2, 0, 2, 0, 2], [4, 0, 0, 0, 0, 0, 0, 0], [0, 0, 0, 0, 0, 2, 0, 0], [0, 0, 0, 0, 0, 0, 0, 0], [0, 0, 0, 0, 0, 0, 0, 0], [0, 0, 0, 0, 0, 0, 0, 0], [0, 0, 0, 0, 0, 0, 0, 0], [0, 0, 0, 0, 0, 0, 0, 0]]"},{"description":"DumbPlayer moves B0:A1","data":"['DumbPlayer', 'B0:A1']"},{"description":"SmartPlayer moves C5:B6","data":"['SmartPlayer', 'C5:B6']"},{"description":"DumbPlayer moves A1:B0","data":"['DumbPlayer', 'A1:B0']"},{"description":"SmartPlayer moves B6:C7","data":"['SmartPlayer', 'B6:C7']"},{"description":"DumbPlayer moves B0:A1","data":"['DumbPlayer', 'B0:A1']"},{"description":"SmartPlayer moves C7:B6","data":"['SmartPlayer', 'C7:B6']"},{"description":"DumbPlayer moves A1:B0","data":"['DumbPlayer', 'A1:B0']"},{"description":"SmartPlayer moves A3:B4","data":"['SmartPlayer', 'A3:B4']"},{"description":"DumbPlayer moves B0:A1","data":"['DumbPlayer', 'B0:A1']"},{"description":"SmartPlayer moves B4:A3","data":"['SmartPlayer', 'B4:A3']","gamestate":"[[0, 4, 0, 2, 0, 2, 0, 2], [0, 0, 0, 0, 0, 0, 2, 0], [0, 0, 0, 0, 0, 0, 0, 0], [0, 0, 0, 0, 0, 0, 0, 0], [0, 0, 0, 0, 0, 0, 0, 0], [0, 0, 0, 0, 0, 0, 0, 0], [0, 0, 0, 0, 0, 0, 0, 0], [0, 0, 0, 0, 0, 0, 0, 0]]"},{"description":"DumbPlayer moves A1:B0","data":"['DumbPlayer', 'A1:B0']"},{"description":"SmartPlayer moves B6:C5","data":"['SmartPlayer', 'B6:C5']"},{"description":"DumbPlayer moves B0:C1","data":"['DumbPlayer', 'B0:C1']"},{"description":"SmartPlayer moves C5:B4","data":"['SmartPlayer', 'C5:B4']"},{"description":"DumbPlayer moves C1:B0","data":"['DumbPlayer', 'C1:B0']"},{"description":"SmartPlayer moves B4:C3","data":"['SmartPlayer', 'B4:C3']"},{"description":"DumbPlayer moves B0:C1","data":"['DumbPlayer', 'B0:C1']"},{"description":"SmartPlayer moves C3:B2","data":"['SmartPlayer', 'C3:B2']"},{"description":"DumbPlayer moves C1:D0","data":"['DumbPlayer', 'C1:D0']"},{"description":"SmartPlayer moves A5:B6","data":"['SmartPlayer', 'A5:B6']","gamestate":"[[0, 0, 0, 2, 0, 0, 0, 2], [0, 0, 2, 0, 0, 0, 2, 0], [0, 0, 0, 0, 0, 0, 0, 0], [4, 0, 0, 0, 0, 0, 0, 0], [0, 0, 0, 0, 0, 0, 0, 0], [0, 0, 0, 0, 0, 0, 0, 0], [0, 0, 0, 0, 0, 0, 0, 0], [0, 0, 0, 0, 0, 0, 0, 0]]"},{"description":"DumbPlayer moves D0:E1","data":"['DumbPlayer', 'D0:E1']"},{"description":"SmartPlayer moves B2:C1","data":"['SmartPlayer', 'B2:C1']"},{"description":"DumbPlayer moves E1:D0","data":"['DumbPlayer', 'E1:D0']"},{"description":"SmartPlayer moves C1:D2","data":"['SmartPlayer', 'C1:D2']"},{"description":"DumbPlayer moves D0:C1","data":"['DumbPlayer', 'D0:C1']"},{"description":"SmartPlayer moves D2:B0","data":"['SmartPlayer', 'D2:B0']"}],"info":"{\"DumbPlayer\": \"black\", \"SmartPlayer\": \"red\"}"}